Metadata-Version: 2.4
Name: adafruit-circuitpython-crickit
Version: 2.3.22
Summary: CircuitPython library for controlling a Crickit robotics board.
Author-email: Adafruit Industries <circuitpython@adafruit.com>
License: MIT
Project-URL: Homepage, https://github.com/adafruit/Adafruit_CircuitPython_Crickit
Keywords: adafruit,crickit,robotics,hardware,micropython,circuitpython
Classifier: Intended Audience :: Developers
Classifier: Topic :: Software Development :: Libraries
Classifier: Topic :: Software Development :: Embedded Systems
Classifier: Topic :: System :: Hardware
Classifier: License :: OSI Approved :: MIT License
Classifier: Programming Language :: Python :: 3
License-File: LICENSE
Requires-Dist: Adafruit-Blinka
Requires-Dist: adafruit-circuitpython-seesaw
Requires-Dist: adafruit-circuitpython-motor
Provides-Extra: optional
Dynamic: license-file
